{
  "db": {
    "user": "$DB_USER",
    "password": "$DB_PASSWORD",
    "host": "db.leavemealone.xyz",
    "port": 27017,
    "name": "leavemealone",
    "encryption": {
      "algorithm": "aes-256-ctr",
      "password": "$DB_ENCRYPT_PASSWORD"
    }
  },
  "google": {
    "redirect": "https://leavemealone.xyz/auth/google/callback"
  },
  "puppeteer": {
    "args": [
      "--no-sandbox",
      "--headless",
      "--disable-gpu",
      "-—disable-dev-tools",
      "--disable-dev-shm-usage",
      "--full-memory-crash-report"
    ],
    "dumpio": false,
    "devtools": false
  },
  "payments": {
    "publishableKey": "pk_live_2thpKDxq45nmO8NBG4wCJr0j",
    "secretKey": "sk_live_3SbQqVsq3kybRISez1MtdeGp"
  }
}
